Workbook

Sheet Dashboard
B2: CallFollow — Outbound Call & Follow-Up Dashboard
B3: Live KPIs from Call_Log. Follow-up status auto-updates with Excel's TODAY() function.
C5: TOTAL CALLS LOGGED | E5: FOLLOW-UPS DUE TODAY | G5: OVERDUE FOLLOW-UPS | I5: CONVERSION RATE
C6: =COUNTA(Call_Log!B3:B22) -> 20 | E6: =COUNTIF(Call_Log!L3:L22,"Due Today") -> 4 | G6: =COUNTIF(Call_Log!L3:L22,"Overdue") -> 3 | I6: =COUNTIF(Call_Log!G3:G22,"Converted")/COUNTA(Call_Log!B3:B22) -> 0.1
C9: CALLS TODAY | E9: INTERESTED | G9: VOICEMAILS LEFT | I9: DO NOT CALL
C10: =COUNTIF(Call_Log!E3:E22,TODAY()) -> 0 | E10: =COUNTIF(Call_Log!G3:G22,"Interested") -> 5 | G10: =COUNTIF(Call_Log!G3:G22,"Left Voicemail") -> 5 | I10: =COUNTIF(Call_Log!G3:G22,"Do Not Call") -> 1
C14: Calls by Outcome | F14: Follow-Up Status | I14: Calls by Campaign
C15: No Answer | D15: =COUNTIF(Call_Log!G3:G22,C15) -> 3 | F15: Overdue | G15: =COUNTIF(Call_Log!L3:L22,F15) -> 3 | I15: Credit Card Promo | J15: =COUNTIF(Call_Log!D3:D22,I15) -> 4
C16: Left Voicemail | D16: =COUNTIF(Call_Log!G3:G22,C16) -> 5 | F16: Due Today | G16: =COUNTIF(Call_Log!L3:L22,F16) -> 4 | I16: CD Rate Campaign | J16: =COUNTIF(Call_Log!D3:D22,I16) -> 4
C17: Callback Scheduled | D17: =COUNTIF(Call_Log!G3:G22,C17) -> 3 | F17: Upcoming | G17: =COUNTIF(Call_Log!L3:L22,F17) -> 8 | I17: Mortgage Refi | J17: =COUNTIF(Call_Log!D3:D22,I17) -> 4
C18: Interested | D18: =COUNTIF(Call_Log!G3:G22,C18) -> 5 | F18: Completed | G18: =COUNTIF(Call_Log!L3:L22,F18) -> 3 | I18: Wealth Management Intro | J18: =COUNTIF(Call_Log!D3:D22,I18) -> 4
C19: Not Interested | D19: =COUNTIF(Call_Log!G3:G22,C19) -> 1 | F19: None | G19: =COUNTIF(Call_Log!L3:L22,F19) -> 2 | I19: Digital Banking Onboarding | J19: =COUNTIF(Call_Log!D3:D22,I19) -> 4
C20: Converted | D20: =COUNTIF(Call_Log!G3:G22,C20) -> 2
C21: Do Not Call | D21: =COUNTIF(Call_Log!G3:G22,C21) -> 1
C40: Note: Follow-Up Status uses Excel TODAY() and updates automatically. Edit Call_Log to add calls. See Follow_Up_Queue sheet for the prioritized callback list.

Sheet Call_Log
B2: Client Name | C2: Phone | D2: Campaign | E2: Call Date | F2: Call Type | G2: Outcome | H2: Follow-Up Date | I2: Priority | J2: Assigned To | K2: Notes | L2: Follow-Up Status | M2: Days Overdue
B3: Maria Gonzalez | C3: (267) 555-0142 | D3: Credit Card Promo | E3: 46217 | F3: Outbound Sales | G3: Left Voicemail | H3: 46226 | I3: Medium | J3: A. Rivera | K3: Left voicemail re: cash-back card offer. | L3: =IF(OR(G3="Converted",G3="Do Not Call"),"Completed",IF(H3="","None",IF(H3<TODAY(),"Overdue",IF(H3=TODAY(),"Due Today","Upcoming")))) -> Overdue | M3: =IF(L3="Overdue",TODAY()-H3,0) -> 3
B4: James Whitfield | C4: (215) 555-0198 | D4: CD Rate Campaign | E4: 46219 | F4: Promotion | G4: Interested | H4: 46228 | I4: High | J4: M. Chen | K4: Interested in 12-mo CD; sent rates. | L4: =IF(OR(G4="Converted",G4="Do Not Call"),"Completed",IF(H4="","None",IF(H4<TODAY(),"Overdue",IF(H4=TODAY(),"Due Today","Upcoming")))) -> Overdue | M4: =IF(L4="Overdue",TODAY()-H4,0) -> 1
B5: Priya Patel | C5: (610) 555-0173 | D5: Mortgage Refi | E5: 46220 | F5: Outbound Sales | G5: Callback Scheduled | H5: 46229 | I5: Medium | J5: S. Patel | K5: Callback scheduled for today re: refi. | L5: =IF(OR(G5="Converted",G5="Do Not Call"),"Completed",IF(H5="","None",IF(H5<TODAY(),"Overdue",IF(H5=TODAY(),"Due Today","Upcoming")))) -> Due Today | M5: =IF(L5="Overdue",TODAY()-H5,0) -> 0
B6: Robert Coleman | C6: (484) 555-0119 | D6: Wealth Management Intro | E6: 46221 | F6: Promotion | G6: No Answer | I6: Low | J6: A. Rivera | K6: No answer, will retry. | L6: =IF(OR(G6="Converted",G6="Do Not Call"),"Completed",IF(H6="","None",IF(H6<TODAY(),"Overdue",IF(H6=TODAY(),"Due Today","Upcoming")))) -> None | M6: =IF(L6="Overdue",TODAY()-H6,0) -> 0
B7: Sarah O'Brien | C7: (215) 555-0167 | D7: Digital Banking Onboarding | E7: 46221 | F7: Outbound Sales | G7: Converted | I7: Medium | J7: M. Chen | K7: Converted — onboarded to mobile app. | L7: =IF(OR(G7="Converted",G7="Do Not Call"),"Completed",IF(H7="","None",IF(H7<TODAY(),"Overdue",IF(H7=TODAY(),"Due Today","Upcoming")))) -> Completed | M7: =IF(L7="Overdue",TODAY()-H7,0) -> 0
B8: Daniel Kim | C8: (267) 555-0184 | D8: Credit Card Promo | E8: 46222 | F8: Outbound Sales | G8: Left Voicemail | H8: 46230 | I8: Medium | J8: S. Patel | K8: Voicemail; 2nd attempt. | L8: =IF(OR(G8="Converted",G8="Do Not Call"),"Completed",IF(H8="","None",IF(H8<TODAY(),"Overdue",IF(H8=TODAY(),"Due Today","Upcoming")))) -> Upcoming | M8: =IF(L8="Overdue",TODAY()-H8,0) -> 0
B9: Emily Rodriguez | C9: (610) 555-0151 | D9: CD Rate Campaign | E9: 46222 | F9: Promotion | G9: Interested | H9: 46231 | I9: High | J9: A. Rivera | K9: Wants 24-mo CD details emailed. | L9: =IF(OR(G9="Converted",G9="Do Not Call"),"Completed",IF(H9="","None",IF(H9<TODAY(),"Overdue",IF(H9=TODAY(),"Due Today","Upcoming")))) -> Upcoming | M9: =IF(L9="Overdue",TODAY()-H9,0) -> 0
B10: Michael Brooks | C10: (215) 555-0133 | D10: Mortgage Refi | E10: 46223 | F10: Outbound Sales | G10: Not Interested | I10: Low | J10: M. Chen | K10: Not interested — rates too high. | L10: =IF(OR(G10="Converted",G10="Do Not Call"),"Completed",IF(H10="","None",IF(H10<TODAY(),"Overdue",IF(H10=TODAY(),"Due Today","Upcoming")))) -> None | M10: =IF(L10="Overdue",TODAY()-H10,0) -> 0
B11: Aisha Williams | C11: (484) 555-0177 | D11: Wealth Management Intro | E11: 46223 | F11: Promotion | G11: Callback Scheduled | H11: 46229 | I11: High | J11: S. Patel | K11: High-priority callback today; estate planning. | L11: =IF(OR(G11="Converted",G11="Do Not Call"),"Completed",IF(H11="","None",IF(H11<TODAY(),"Overdue",IF(H11=TODAY(),"Due Today","Upcoming")))) -> Due Today | M11: =IF(L11="Overdue",TODAY()-H11,0) -> 0
B12: Thomas Nguyen | C12: (267) 555-0146 | D12: Digital Banking Onboarding | E12: 46224 | F12: Outbound Sales | G12: Left Voicemail | H12: 46227 | I12: Medium | J12: A. Rivera | K12: Voicemail re: digital banking setup. | L12: =IF(OR(G12="Converted",G12="Do Not Call"),"Completed",IF(H12="","None",IF(H12<TODAY(),"Overdue",IF(H12=TODAY(),"Due Today","Upcoming")))) -> Overdue | M12: =IF(L12="Overdue",TODAY()-H12,0) -> 2
B13: Jennifer Carter | C13: (215) 555-0192 | D13: Credit Card Promo | E13: 46224 | F13: Outbound Sales | G13: Interested | H13: 46232 | I13: Medium | J13: M. Chen | K13: Interested in balance transfer card. | L13: =IF(OR(G13="Converted",G13="Do Not Call"),"Completed",IF(H13="","None",IF(H13<TODAY(),"Overdue",IF(H13=TODAY(),"Due Today","Upcoming")))) -> Upcoming | M13: =IF(L13="Overdue",TODAY()-H13,0) -> 0
B14: David Schmidt | C14: (610) 555-0125 | D14: CD Rate Campaign | E14: 46225 | F14: Promotion | G14: Do Not Call | I14: Low | J14: A. Rivera | K14: Asked to be removed from CD list. | L14: =IF(OR(G14="Converted",G14="Do Not Call"),"Completed",IF(H14="","None",IF(H14<TODAY(),"Overdue",IF(H14=TODAY(),"Due Today","Upcoming")))) -> Completed | M14: =IF(L14="Overdue",TODAY()-H14,0) -> 0
B15: Linda Martinez | C15: (484) 555-0188 | D15: Mortgage Refi | E15: 46225 | F15: Outbound Sales | G15: No Answer | H15: 46230 | I15: Medium | J15: S. Patel | K15: No answer; refi follow-up tomorrow. | L15: =IF(OR(G15="Converted",G15="Do Not Call"),"Completed",IF(H15="","None",IF(H15<TODAY(),"Overdue",IF(H15=TODAY(),"Due Today","Upcoming")))) -> Upcoming | M15: =IF(L15="Overdue",TODAY()-H15,0) -> 0
B16: Kevin O'Connor | C16: (267) 555-0111 | D16: Wealth Management Intro | E16: 46226 | F16: Promotion | G16: Interested | H16: 46231 | I16: High | J16: A. Rivera | K16: Interested in advisory consult. | L16: =IF(OR(G16="Converted",G16="Do Not Call"),"Completed",IF(H16="","None",IF(H16<TODAY(),"Overdue",IF(H16=TODAY(),"Due Today","Upcoming")))) -> Upcoming | M16: =IF(L16="Overdue",TODAY()-H16,0) -> 0
B17: Rachel Goldman | C17: (215) 555-0159 | D17: Digital Banking Onboarding | E17: 46226 | F17: Outbound Sales | G17: Callback Scheduled | H17: 46229 | I17: Medium | J17: M. Chen | K17: Callback today re: online statements. | L17: =IF(OR(G17="Converted",G17="Do Not Call"),"Completed",IF(H17="","None",IF(H17<TODAY(),"Overdue",IF(H17=TODAY(),"Due Today","Upcoming")))) -> Due Today | M17: =IF(L17="Overdue",TODAY()-H17,0) -> 0
B18: Carlos Rivera | C18: (610) 555-0140 | D18: Credit Card Promo | E18: 46227 | F18: Outbound Sales | G18: Converted | I18: Medium | J18: S. Patel | K18: Converted — approved for credit card. | L18: =IF(OR(G18="Converted",G18="Do Not Call"),"Completed",IF(H18="","None",IF(H18<TODAY(),"Overdue",IF(H18=TODAY(),"Due Today","Upcoming")))) -> Completed | M18: =IF(L18="Overdue",TODAY()-H18,0) -> 0
B19: Nicole Anderson | C19: (484) 555-0163 | D19: CD Rate Campaign | E19: 46227 | F19: Promotion | G19: Left Voicemail | H19: 46233 | I19: Low | J19: A. Rivera | K19: Voicemail; CD ladder interest. | L19: =IF(OR(G19="Converted",G19="Do Not Call"),"Completed",IF(H19="","None",IF(H19<TODAY(),"Overdue",IF(H19=TODAY(),"Due Today","Upcoming")))) -> Upcoming | M19: =IF(L19="Overdue",TODAY()-H19,0) -> 0
B20: Brian Sullivan | C20: (267) 555-0170 | D20: Mortgage Refi | E20: 46228 | F20: Outbound Sales | G20: No Answer | H20: 46229 | I20: High | J20: M. Chen | K20: No answer; refi callback today. | L20: =IF(OR(G20="Converted",G20="Do Not Call"),"Completed",IF(H20="","None",IF(H20<TODAY(),"Overdue",IF(H20=TODAY(),"Due Today","Upcoming")))) -> Due Today | M20: =IF(L20="Overdue",TODAY()-H20,0) -> 0
B21: Sophia Lee | C21: (215) 555-0129 | D21: Wealth Management Intro | E21: 46228 | F21: Promotion | G21: Interested | H21: 46230 | I21: Medium | J21: S. Patel | K21: Wants wealth mgmt brochures. | L21: =IF(OR(G21="Converted",G21="Do Not Call"),"Completed",IF(H21="","None",IF(H21<TODAY(),"Overdue",IF(H21=TODAY(),"Due Today","Upcoming")))) -> Upcoming | M21: =IF(L21="Overdue",TODAY()-H21,0) -> 0
B22: Marcus Johnson | C22: (610) 555-0186 | D22: Digital Banking Onboarding | E22: 46228 | F22: Outbound Sales | G22: Left Voicemail | H22: 46231 | I22: Low | J22: A. Rivera | K22: Voicemail re: bill pay setup. | L22: =IF(OR(G22="Converted",G22="Do Not Call"),"Completed",IF(H22="","None",IF(H22<TODAY(),"Overdue",IF(H22=TODAY(),"Due Today","Upcoming")))) -> Upcoming | M22: =IF(L22="Overdue",TODAY()-H22,0) -> 0

Sheet Follow_Up_Queue
B2: Follow-Up Queue — due today & overdue (live formulas)
B3: Priority | C3: Client Name | D3: Phone | E3: Campaign | F3: Outcome | G3: Follow-Up Date | H3: Status | I3: Days Overdue
B4: =IF(OR(Call_Log!L3="Overdue",Call_Log!L3="Due Today"),Call_Log!I3,"") -> Medium | C4: =IF(OR(Call_Log!L3="Overdue",Call_Log!L3="Due Today"),Call_Log!B3,"") -> Maria Gonzalez | D4: =IF(OR(Call_Log!L3="Overdue",Call_Log!L3="Due Today"),Call_Log!C3,"") -> (267) 555-0142 | E4: =IF(OR(Call_Log!L3="Overdue",Call_Log!L3="Due Today"),Call_Log!D3,"") -> Credit Card Promo | F4: =IF(OR(Call_Log!L3="Overdue",Call_Log!L3="Due Today"),Call_Log!G3,"") -> Left Voicemail | G4: =IF(OR(Call_Log!L3="Overdue",Call_Log!L3="Due Today"),Call_Log!H3,"") -> 46226 | H4: =IF(OR(Call_Log!L3="Overdue",Call_Log!L3="Due Today"),Call_Log!L3,"") -> Overdue | I4: =IF(OR(Call_Log!L3="Overdue",Call_Log!L3="Due Today"),Call_Log!M3,"") -> 3
B5: =IF(OR(Call_Log!L4="Overdue",Call_Log!L4="Due Today"),Call_Log!I4,"") -> High | C5: =IF(OR(Call_Log!L4="Overdue",Call_Log!L4="Due Today"),Call_Log!B4,"") -> James Whitfield | D5: =IF(OR(Call_Log!L4="Overdue",Call_Log!L4="Due Today"),Call_Log!C4,"") -> (215) 555-0198 | E5: =IF(OR(Call_Log!L4="Overdue",Call_Log!L4="Due Today"),Call_Log!D4,"") -> CD Rate Campaign | F5: =IF(OR(Call_Log!L4="Overdue",Call_Log!L4="Due Today"),Call_Log!G4,"") -> Interested | G5: =IF(OR(Call_Log!L4="Overdue",Call_Log!L4="Due Today"),Call_Log!H4,"") -> 46228 | H5: =IF(OR(Call_Log!L4="Overdue",Call_Log!L4="Due Today"),Call_Log!L4,"") -> Overdue | I5: =IF(OR(Call_Log!L4="Overdue",Call_Log!L4="Due Today"),Call_Log!M4,"") -> 1
B6: =IF(OR(Call_Log!L5="Overdue",Call_Log!L5="Due Today"),Call_Log!I5,"") -> Medium | C6: =IF(OR(Call_Log!L5="Overdue",Call_Log!L5="Due Today"),Call_Log!B5,"") -> Priya Patel | D6: =IF(OR(Call_Log!L5="Overdue",Call_Log!L5="Due Today"),Call_Log!C5,"") -> (610) 555-0173 | E6: =IF(OR(Call_Log!L5="Overdue",Call_Log!L5="Due Today"),Call_Log!D5,"") -> Mortgage Refi | F6: =IF(OR(Call_Log!L5="Overdue",Call_Log!L5="Due Today"),Call_Log!G5,"") -> Callback Scheduled | G6: =IF(OR(Call_Log!L5="Overdue",Call_Log!L5="Due Today"),Call_Log!H5,"") -> 46229 | H6: =IF(OR(Call_Log!L5="Overdue",Call_Log!L5="Due Today"),Call_Log!L5,"") -> Due Today | I6: =IF(OR(Call_Log!L5="Overdue",Call_Log!L5="Due Today"),Call_Log!M5,"") -> 0
B7: =IF(OR(Call_Log!L6="Overdue",Call_Log!L6="Due Today"),Call_Log!I6,"") | C7: =IF(OR(Call_Log!L6="Overdue",Call_Log!L6="Due Today"),Call_Log!B6,"") | D7: =IF(OR(Call_Log!L6="Overdue",Call_Log!L6="Due Today"),Call_Log!C6,"") | E7: =IF(OR(Call_Log!L6="Overdue",Call_Log!L6="Due Today"),Call_Log!D6,"") | F7: =IF(OR(Call_Log!L6="Overdue",Call_Log!L6="Due Today"),Call_Log!G6,"") | G7: =IF(OR(Call_Log!L6="Overdue",Call_Log!L6="Due Today"),Call_Log!H6,"") | H7: =IF(OR(Call_Log!L6="Overdue",Call_Log!L6="Due Today"),Call_Log!L6,"") | I7: =IF(OR(Call_Log!L6="Overdue",Call_Log!L6="Due Today"),Call_Log!M6,"")
B8: =IF(OR(Call_Log!L7="Overdue",Call_Log!L7="Due Today"),Call_Log!I7,"") | C8: =IF(OR(Call_Log!L7="Overdue",Call_Log!L7="Due Today"),Call_Log!B7,"") | D8: =IF(OR(Call_Log!L7="Overdue",Call_Log!L7="Due Today"),Call_Log!C7,"") | E8: =IF(OR(Call_Log!L7="Overdue",Call_Log!L7="Due Today"),Call_Log!D7,"") | F8: =IF(OR(Call_Log!L7="Overdue",Call_Log!L7="Due Today"),Call_Log!G7,"") | G8: =IF(OR(Call_Log!L7="Overdue",Call_Log!L7="Due Today"),Call_Log!H7,"") | H8: =IF(OR(Call_Log!L7="Overdue",Call_Log!L7="Due Today"),Call_Log!L7,"") | I8: =IF(OR(Call_Log!L7="Overdue",Call_Log!L7="Due Today"),Call_Log!M7,"")
B9: =IF(OR(Call_Log!L8="Overdue",Call_Log!L8="Due Today"),Call_Log!I8,"") | C9: =IF(OR(Call_Log!L8="Overdue",Call_Log!L8="Due Today"),Call_Log!B8,"") | D9: =IF(OR(Call_Log!L8="Overdue",Call_Log!L8="Due Today"),Call_Log!C8,"") | E9: =IF(OR(Call_Log!L8="Overdue",Call_Log!L8="Due Today"),Call_Log!D8,"") | F9: =IF(OR(Call_Log!L8="Overdue",Call_Log!L8="Due Today"),Call_Log!G8,"") | G9: =IF(OR(Call_Log!L8="Overdue",Call_Log!L8="Due Today"),Call_Log!H8,"") | H9: =IF(OR(Call_Log!L8="Overdue",Call_Log!L8="Due Today"),Call_Log!L8,"") | I9: =IF(OR(Call_Log!L8="Overdue",Call_Log!L8="Due Today"),Call_Log!M8,"")
B10: =IF(OR(Call_Log!L9="Overdue",Call_Log!L9="Due Today"),Call_Log!I9,"") | C10: =IF(OR(Call_Log!L9="Overdue",Call_Log!L9="Due Today"),Call_Log!B9,"") | D10: =IF(OR(Call_Log!L9="Overdue",Call_Log!L9="Due Today"),Call_Log!C9,"") | E10: =IF(OR(Call_Log!L9="Overdue",Call_Log!L9="Due Today"),Call_Log!D9,"") | F10: =IF(OR(Call_Log!L9="Overdue",Call_Log!L9="Due Today"),Call_Log!G9,"") | G10: =IF(OR(Call_Log!L9="Overdue",Call_Log!L9="Due Today"),Call_Log!H9,"") | H10: =IF(OR(Call_Log!L9="Overdue",Call_Log!L9="Due Today"),Call_Log!L9,"") | I10: =IF(OR(Call_Log!L9="Overdue",Call_Log!L9="Due Today"),Call_Log!M9,"")
B11: =IF(OR(Call_Log!L10="Overdue",Call_Log!L10="Due Today"),Call_Log!I10,"") | C11: =IF(OR(Call_Log!L10="Overdue",Call_Log!L10="Due Today"),Call_Log!B10,"") | D11: =IF(OR(Call_Log!L10="Overdue",Call_Log!L10="Due Today"),Call_Log!C10,"") | E11: =IF(OR(Call_Log!L10="Overdue",Call_Log!L10="Due Today"),Call_Log!D10,"") | F11: =IF(OR(Call_Log!L10="Overdue",Call_Log!L10="Due Today"),Call_Log!G10,"") | G11: =IF(OR(Call_Log!L10="Overdue",Call_Log!L10="Due Today"),Call_Log!H10,"") | H11: =IF(OR(Call_Log!L10="Overdue",Call_Log!L10="Due Today"),Call_Log!L10,"") | I11: =IF(OR(Call_Log!L10="Overdue",Call_Log!L10="Due Today"),Call_Log!M10,"")
B12: =IF(OR(Call_Log!L11="Overdue",Call_Log!L11="Due Today"),Call_Log!I11,"") -> High | C12: =IF(OR(Call_Log!L11="Overdue",Call_Log!L11="Due Today"),Call_Log!B11,"") -> Aisha Williams | D12: =IF(OR(Call_Log!L11="Overdue",Call_Log!L11="Due Today"),Call_Log!C11,"") -> (484) 555-0177 | E12: =IF(OR(Call_Log!L11="Overdue",Call_Log!L11="Due Today"),Call_Log!D11,"") -> Wealth Management Intro | F12: =IF(OR(Call_Log!L11="Overdue",Call_Log!L11="Due Today"),Call_Log!G11,"") -> Callback Scheduled | G12: =IF(OR(Call_Log!L11="Overdue",Call_Log!L11="Due Today"),Call_Log!H11,"") -> 46229 | H12: =IF(OR(Call_Log!L11="Overdue",Call_Log!L11="Due Today"),Call_Log!L11,"") -> Due Today | I12: =IF(OR(Call_Log!L11="Overdue",Call_Log!L11="Due Today"),Call_Log!M11,"") -> 0
B13: =IF(OR(Call_Log!L12="Overdue",Call_Log!L12="Due Today"),Call_Log!I12,"") -> Medium | C13: =IF(OR(Call_Log!L12="Overdue",Call_Log!L12="Due Today"),Call_Log!B12,"") -> Thomas Nguyen | D13: =IF(OR(Call_Log!L12="Overdue",Call_Log!L12="Due Today"),Call_Log!C12,"") -> (267) 555-0146 | E13: =IF(OR(Call_Log!L12="Overdue",Call_Log!L12="Due Today"),Call_Log!D12,"") -> Digital Banking Onboarding | F13: =IF(OR(Call_Log!L12="Overdue",Call_Log!L12="Due Today"),Call_Log!G12,"") -> Left Voicemail | G13: =IF(OR(Call_Log!L12="Overdue",Call_Log!L12="Due Today"),Call_Log!H12,"") -> 46227 | H13: =IF(OR(Call_Log!L12="Overdue",Call_Log!L12="Due Today"),Call_Log!L12,"") -> Overdue | I13: =IF(OR(Call_Log!L12="Overdue",Call_Log!L12="Due Today"),Call_Log!M12,"") -> 2
B14: =IF(OR(Call_Log!L13="Overdue",Call_Log!L13="Due Today"),Call_Log!I13,"") | C14: =IF(OR(Call_Log!L13="Overdue",Call_Log!L13="Due Today"),Call_Log!B13,"") | D14: =IF(OR(Call_Log!L13="Overdue",Call_Log!L13="Due Today"),Call_Log!C13,"") | E14: =IF(OR(Call_Log!L13="Overdue",Call_Log!L13="Due Today"),Call_Log!D13,"") | F14: =IF(OR(Call_Log!L13="Overdue",Call_Log!L13="Due Today"),Call_Log!G13,"") | G14: =IF(OR(Call_Log!L13="Overdue",Call_Log!L13="Due Today"),Call_Log!H13,"") | H14: =IF(OR(Call_Log!L13="Overdue",Call_Log!L13="Due Today"),Call_Log!L13,"") | I14: =IF(OR(Call_Log!L13="Overdue",Call_Log!L13="Due Today"),Call_Log!M13,"")
B15: =IF(OR(Call_Log!L14="Overdue",Call_Log!L14="Due Today"),Call_Log!I14,"") | C15: =IF(OR(Call_Log!L14="Overdue",Call_Log!L14="Due Today"),Call_Log!B14,"") | D15: =IF(OR(Call_Log!L14="Overdue",Call_Log!L14="Due Today"),Call_Log!C14,"") | E15: =IF(OR(Call_Log!L14="Overdue",Call_Log!L14="Due Today"),Call_Log!D14,"") | F15: =IF(OR(Call_Log!L14="Overdue",Call_Log!L14="Due Today"),Call_Log!G14,"") | G15: =IF(OR(Call_Log!L14="Overdue",Call_Log!L14="Due Today"),Call_Log!H14,"") | H15: =IF(OR(Call_Log!L14="Overdue",Call_Log!L14="Due Today"),Call_Log!L14,"") | I15: =IF(OR(Call_Log!L14="Overdue",Call_Log!L14="Due Today"),Call_Log!M14,"")
... B23: =IF(OR(Call_Log!L22="Overdue",Call_Log!L22="Due Today"),Call_Log!I22,"") | C23: =IF(OR(Call_Log!L22="Overdue",Call_Log!L22="Due Today"),Call_Log!B22,"") | D23: =IF(OR(Call_Log!L22="Overdue",Call_Log!L22="Due Today"),Call_Log!C22,"") | E23: =IF(OR(Call_Log!L22="Overdue",Call_Log!L22="Due Today"),Call_Log!D22,"") | F23: =IF(OR(Call_Log!L22="Overdue",Call_Log!L22="Due Today"),Call_Log!G22,"") | G23: =IF(OR(Call_Log!L22="Overdue",Call_Log!L22="Due Today"),Call_Log!H22,"") | H23: =IF(OR(Call_Log!L22="Overdue",Call_Log!L22="Due Today"),Call_Log!L22,"") | I23: =IF(OR(Call_Log!L22="Overdue",Call_Log!L22="Due Today"),Call_Log!M22,"")
